django_urlbrevity-0.1.0.dist-info/DESCRIPTION.rst
django_urlbrevity-0.1.0.dist-info/METADATA
django_urlbrevity-0.1.0.dist-info/metadata.json
django_urlbrevity-0.1.0.dist-info/RECORD
django_urlbrevity-0.1.0.dist-info/top_level.txt
django_urlbrevity-0.1.0.dist-info/WHEEL
urlbrevity/__init__.py
urlbrevity/errors.py
urlbrevity/feeds.py
urlbrevity/signals.py
urlbrevity/sitemaps.py
urlbrevity/test_management_commands.py
urlbrevity/test_sitemaps.py
urlbrevity/test_templatetags.py
urlbrevity/test_urlconf.py
urlbrevity/test_utils.py
urlbrevity/test_views.py
urlbrevity/urlconf.py
urlbrevity/utils.py
urlbrevity/views.py
urlbrevity/management/__init__.py
urlbrevity/management/commands/__init__.py
urlbrevity/management/commands/urlbrevity.py
urlbrevity/templatetags/__init__.py
urlbrevity/templatetags/urlbrevity.py
