Metadata-Version: 2.0
Name: django-urlbrevity
Version: 0.1.0
Summary: UNKNOWN
Home-page: UNKNOWN
Author: Keryn Knight
Author-email: python-package@kerynknight.com
License: BSD License
Keywords: django shortURLs
Platform: OS Independent
Classifier: Development Status :: 3 - Alpha
Classifier: Environment :: Web Environment
Classifier: Framework :: Django
Classifier: Intended Audience :: Developers
Classifier: Operating System :: OS Independent
Classifier: Programming Language :: Python :: 2.6
Classifier: Programming Language :: Python :: 2.7
Classifier: Programming Language :: Python :: 3.3
Classifier: Programming Language :: Python :: Implementation :: PyPy
Classifier: Natural Language :: English
Classifier: Topic :: Internet :: WWW/HTTP :: Site Management
Classifier: License :: OSI Approved :: BSD License
Requires-Dist: Django (>=1.4)
Requires-Dist: hashids (>=1.0)
